[{"start":1833,"end":5433,"text":"Manejaba un taxista..."},{"start":5433,"end":8233,"text":"cuando una somnolienta persona sorda se afan\u00f3"},{"start":8233,"end":12033,"text":"porque llegaba tarde a su cita."},{"start":12033,"end":15576,"text":"Baj\u00f3 las escaleras,"},{"start":15576,"end":19171,"text":"pidi\u00f3 un Uber,"},{"start":19171,"end":25933,"text":"y lleg\u00f3 el taxi."},{"start":25933,"end":29033,"text":"Iba subiendo su maleta al auto,"},{"start":29033,"end":32333,"text":"mientoras el taxista le pregunt\u00f3 a d\u00f3nde iba."},{"start":32333,"end":34533,"text":"El sordo cerr\u00f3 la puerta y dijo:"},{"start":34533,"end":38199,"text":"Ah perd\u00f3n, soy sordo."},{"start":38200,"end":43433,"text":"El taxista: A d\u00f3nde vas?"},{"start":43433,"end":47075,"text":"El sordo le indic\u00f3 que siguiese derecho."},{"start":47075,"end":50899,"text":"El taxista conduci\u00f3 derecho"},{"start":50900,"end":53533,"text":"y no sab\u00eda qu\u00e9 hacer con su pasajero sordo."},{"start":53533,"end":59066,"text":"Lo ve\u00eda por el retrovisor t continuaba manejando..."},{"start":59066,"end":60999,"text":"\"Ahora a la izquierda\""},{"start":61000,"end":64733,"text":"OK, a la izquierda."},{"start":64733,"end":67066,"text":"Segu\u00eda manejando"},{"start":67066,"end":71166,"text":"y se detuvo en el sem\u00e1foro con la luz roja."},{"start":71166,"end":74599,"text":"Espero a que las personas pasar\u00e1n."},{"start":74600,"end":77100,"text":"El sordo estaba muy preocupado"},{"start":77100,"end":79100,"text":"porque ya era tarde."},{"start":79100,"end":82166,"text":"\"Por favor, v\u00e1monos, ya es tarde, ya es tarde\""},{"start":82166,"end":85232,"text":"\u00a1Espere, espere, est\u00e1 en rojo!"},{"start":85233,"end":87765,"text":"\u00a1V\u00e1monos por favor!"},{"start":87765,"end":90899,"text":"El taxista obedeci\u00f3"},{"start":90900,"end":93866,"text":"y se sigui\u00f3 el rojo."},{"start":93866,"end":98499,"text":"El sordo muy preocupado porque ya era tarde."},{"start":98500,"end":102800,"text":"\"Oye, si te toca una luz roja no le hagas caso\""},{"start":102800,"end":107900,"text":"\"T\u00fa contin\u00faa, porque ya es muy tarde\""},{"start":107900,"end":112433,"text":"En eso aparece una patrulla"},{"start":112433,"end":115199,"text":"y le dijo que se orillara."},{"start":115200,"end":119700,"text":"Se orill\u00f3 y le dijo: \u00bfOiga, que pas\u00f3?"},{"start":119700,"end":122000,"text":"Se pas\u00f3 la luz roja."},{"start":122000,"end":129066,"text":"\"Ah s\u00ed, disculpe, mi pasajero es sordo\""},{"start":129066,"end":133599,"text":"Le habl\u00f3 y en efecto, la persona sorda no le escuchaba."},{"start":133600,"end":136233,"text":"\"Bueno est\u00e1 bien,"},{"start":136233,"end":139299,"text":"le dar\u00e9 una mordida\""},{"start":139300,"end":143233,"text":"Se la dio y continu\u00f3 conduciendo."},{"start":143233,"end":146166,"text":"La persona sorda ya estaba muy desesperada"},{"start":146166,"end":148966,"text":"y le pidi\u00f3 que cambiaran de lugar."},{"start":148966,"end":154732,"text":"El chofer acepto y ahora el sordo manejaba."},{"start":154733,"end":161199,"text":"Y se pasaba todas las luces rojas."},{"start":161200,"end":167266,"text":"El chofer estaba sorprendido de que se pasara los altos."},{"start":167266,"end":172366,"text":"Un polic\u00eda los vio"},{"start":172366,"end":174899,"text":"y los sigui\u00f3 por un tiempo."},{"start":174900,"end":179433,"text":"Y le dijo: \u00a1Or\u00edllese!"},{"start":179433,"end":183199,"text":"Y se orill\u00f3."},{"start":183200,"end":185300,"text":"\u00bfQu\u00e9 pas\u00f3?"},{"start":185300,"end":189266,"text":"\"Ay, yo soy sordo, disculpe\""},{"start":189266,"end":193032,"text":"Y el polic\u00eda: Est\u00e1 bien, contin\u00fae."},{"start":193033,"end":198433,"text":"El chofer muy sorprendido: \u00a1Solo porque es sordo!"},{"start":198433,"end":203833,"text":"\u00a1Hace un momento me detuvieron y tuve que dar mordida!"},{"start":203833,"end":209299,"text":"\u00a1Aprender\u00e9!"},{"start":209300,"end":217133,"text":"El sordo lleg\u00f3 a su destino, pag\u00f3 al chofer y se fue."},{"start":217133,"end":219999,"text":"Aprendi\u00f3 el chofer de su experiencia."},{"start":220000,"end":224933,"text":"Sub\u00ed\u00f3 otro pasaje y ten\u00eda que llegar r\u00e1pido a su destino."},{"start":224933,"end":231366,"text":"Record\u00f3 la experiencia de su pasajero sordo."},{"start":231366,"end":238132,"text":"Arranc\u00f3, conducci\u00f3 y se pas\u00f3 los altos."},{"start":238133,"end":241333,"text":"Un polic\u00eda lo detuvo y le dijo: Yo soy sordo."},{"start":241333,"end":243899,"text":"El polic\u00eda le dijo: OK, espere."},{"start":243900,"end":249100,"text":"Fue por un manual y le empez\u00f3 a decir con se\u00f1as."},{"start":249100,"end":250902,"text":"Y el ch\u00f3fer: \u00bfQu\u00e9?"},{"start":250902,"end":252671,"text":"\"Perd\u00f3n, h\u00e1bleme\""},{"start":252671,"end":259620,"text":"Y as\u00ed fue como el polic\u00eda se dio cuenta de que era oyente."}]